Proyectoiva/main.py
Proyectoiva/mensajes/__init__.py
Proyectoiva/mensajes/saludo.py
proyectoiva-0.1.1.dist-info/entry_points.txt
proyectoiva-0.1.1.dist-info/WHEEL
proyectoiva-0.1.1.dist-info/METADATA
proyectoiva-0.1.1.dist-info/RECORD
