Metadata-Version: 2.1
Name: proyectoiva
Version: 0.1.1
Summary: Proyecto se trata de Arquitectura interior
License: MIT
Keywords: Diseño Interior
Author: Imanazco
Author-email: ivanna_ao97@outlook.es
Requires-Python: >=3.8,<4.0
Classifier: License :: OSI Approved :: MIT License
Classifier: Programming Language :: Python :: 3
Classifier: Programming Language :: Python :: 3.10
Classifier: Programming Language :: Python :: 3.8
Classifier: Programming Language :: Python :: 3.9
